pfandbon/__init__.py
pfandbon/barcode_utils.py
pfandbon/config.py
pfandbon/pfandbon_generator.py
generate_pfandbon-0.1.0.dist-info/LICENSE
generate_pfandbon-0.1.0.dist-info/METADATA
generate_pfandbon-0.1.0.dist-info/WHEEL
generate_pfandbon-0.1.0.dist-info/top_level.txt
generate_pfandbon-0.1.0.dist-info/RECORD
