Metadata-Version: 2.1
Name: generate_pfandbon
Version: 0.1.0
Summary: Ein Modul zur Generierung von Pfandbons mit allen Barcode-Versionen
Home-page: https://github.com/yourusername/pfandbon-generator
Author: DeeptTutorials
Author-email: deeptutorials.sellpass@gmail.com
Classifier: Programming Language :: Python :: 3
Classifier: License :: OSI Approved :: MIT License
Classifier: Operating System :: OS Independent
Requires-Python: >=3.6
License-File: LICENSE
Requires-Dist: Pillow >=8.0.0
